{"created": 1775174842.94323, "duration": 0.0689229965209961, "exitcode": 0, "root": "/home/runner/work/public-script-server/public-script-server", "environment": {}, "summary": {"passed": 9, "total": 9, "collected": 9}, "collectors": [{"nodeid": "", "outcome": "passed", "result": [{"nodeid": ".", "type": "Dir"}]}, {"nodeid": "reports/history", "outcome": "passed", "result": []}, {"nodeid": "reports", "outcome": "passed", "result": [{"nodeid": "reports/history", "type": "Dir"}]}, {"nodeid": "static/answers", "outcome": "passed", "result": []}, {"nodeid": "static/audio", "outcome": "passed", "result": []}, {"nodeid": "static", "outcome": "passed", "result": [{"nodeid": "static/answers", "type": "Dir"}, {"nodeid": "static/audio", "type": "Dir"}]}, {"nodeid": "templates", "outcome": "passed", "result": []}, {"nodeid": "tests/api/test_basic_routes.py", "outcome": "passed", "result": [{"nodeid": "tests/api/test_basic_routes.py::test_homepage_loads", "type": "Function", "lineno": 0}, {"nodeid": "tests/api/test_basic_routes.py::test_personas_endpoint", "type": "Function", "lineno": 4}, {"nodeid": "tests/api/test_basic_routes.py::test_sass_returns_line", "type": "Function", "lineno": 11}]}, {"nodeid": "tests/api/test_chat.py", "outcome": "passed", "result": [{"nodeid": "tests/api/test_chat.py::test_chat_returns_reply", "type": "Function", "lineno": 2}]}, {"nodeid": "tests/api/test_walkie.py", "outcome": "passed", "result": [{"nodeid": "tests/api/test_walkie.py::test_walkie_locked_persona", "type": "Function", "lineno": 0}]}, {"nodeid": "tests/api", "outcome": "passed", "result": [{"nodeid": "tests/api/test_basic_routes.py", "type": "Module"}, {"nodeid": "tests/api/test_chat.py", "type": "Module"}, {"nodeid": "tests/api/test_walkie.py", "type": "Module"}]}, {"nodeid": "tests/unit/test_personas.py", "outcome": "passed", "result": [{"nodeid": "tests/unit/test_personas.py::test_default_persona_unlocked", "type": "Function", "lineno": 2}, {"nodeid": "tests/unit/test_personas.py::test_elissatron_locked_without_key", "type": "Function", "lineno": 5}, {"nodeid": "tests/unit/test_personas.py::test_elissatron_unlocks_with_correct_key", "type": "Function", "lineno": 9}, {"nodeid": "tests/unit/test_personas.py::test_get_persona_defaults_to_maxnet", "type": "Function", "lineno": 13}]}, {"nodeid": "tests/unit", "outcome": "passed", "result": [{"nodeid": "tests/unit/test_personas.py", "type": "Module"}]}, {"nodeid": "tests", "outcome": "passed", "result": [{"nodeid": "tests/api", "type": "Dir"}, {"nodeid": "tests/unit", "type": "Dir"}]}, {"nodeid": ".", "outcome": "passed", "result": [{"nodeid": "reports", "type": "Dir"}, {"nodeid": "static", "type": "Dir"}, {"nodeid": "templates", "type": "Dir"}, {"nodeid": "tests", "type": "Package"}]}], "tests": [{"nodeid": "tests/api/test_basic_routes.py::test_homepage_loads", "lineno": 0, "outcome": "passed", "keywords": ["test_homepage_loads", "test_basic_routes.py", "api", "tests", "public-script-server", ""], "setup": {"duration": 0.0014838179999969725, "outcome": "passed"}, "call": {"duration": 0.012613588000021991, "outcome": "passed"}, "teardown": {"duration": 0.0001483240000652586, "outcome": "passed"}}, {"nodeid": "tests/api/test_basic_routes.py::test_personas_endpoint", "lineno": 4, "outcome": "passed", "keywords": ["test_personas_endpoint", "test_basic_routes.py", "api", "tests", "public-script-server", ""], "setup": {"duration": 0.00025632299991684704, "outcome": "passed"}, "call": {"duration": 0.0005743809999785299, "outcome": "passed"}, "teardown": {"duration": 0.00011113300001852622, "outcome": "passed"}}, {"nodeid": "tests/api/test_basic_routes.py::test_sass_returns_line", "lineno": 11, "outcome": "passed", "keywords": ["test_sass_returns_line", "test_basic_routes.py", "api", "tests", "public-script-server", ""], "setup": {"duration": 0.00019611300001542986, "outcome": "passed"}, "call": {"duration": 0.00046967799994490633, "outcome": "passed"}, "teardown": {"duration": 0.00010766100001546874, "outcome": "passed"}}, {"nodeid": "tests/api/test_chat.py::test_chat_returns_reply", "lineno": 2, "outcome": "passed", "keywords": ["test_chat_returns_reply", "__wrapped__", "patchings", "test_chat.py", "api", "tests", "public-script-server", ""], "setup": {"duration": 0.0002356500000360029, "outcome": "passed"}, "call": {"duration": 0.0012723749999850043, "outcome": "passed"}, "teardown": {"duration": 0.00010883700008434971, "outcome": "passed"}}, {"nodeid": "tests/api/test_walkie.py::test_walkie_locked_persona", "lineno": 0, "outcome": "passed", "keywords": ["test_walkie_locked_persona", "test_walkie.py", "api", "tests", "public-script-server", ""], "setup": {"duration": 0.00022667099995032913, "outcome": "passed"}, "call": {"duration": 0.0011306760000024951, "outcome": "passed"}, "teardown": {"duration": 0.00010819700003139587, "outcome": "passed"}}, {"nodeid": "tests/unit/test_personas.py::test_default_persona_unlocked", "lineno": 2, "outcome": "passed", "keywords": ["test_default_persona_unlocked", "test_personas.py", "unit", "tests", "public-script-server", ""], "setup": {"duration": 0.00012760000004163885, "outcome": "passed"}, "call": {"duration": 9.862499996415863e-05, "outcome": "passed"}, "teardown": {"duration": 7.496099999571015e-05, "outcome": "passed"}}, {"nodeid": "tests/unit/test_personas.py::test_elissatron_locked_without_key", "lineno": 5, "outcome": "passed", "keywords": ["test_elissatron_locked_without_key", "test_personas.py", "unit", "tests", "public-script-server", ""], "setup": {"duration": 0.00011770400010391313, "outcome": "passed"}, "call": {"duration": 9.03489999473095e-05, "outcome": "passed"}, "teardown": {"duration": 8.734099992580013e-05, "outcome": "passed"}}, {"nodeid": "tests/unit/test_personas.py::test_elissatron_unlocks_with_correct_key", "lineno": 9, "outcome": "passed", "keywords": ["test_elissatron_unlocks_with_correct_key", "test_personas.py", "unit", "tests", "public-script-server", ""], "setup": {"duration": 0.0001136560000531972, "outcome": "passed"}, "call": {"duration": 8.962300000803225e-05, "outcome": "passed"}, "teardown": {"duration": 8.880000007138733e-05, "outcome": "passed"}}, {"nodeid": "tests/unit/test_personas.py::test_get_persona_defaults_to_maxnet", "lineno": 13, "outcome": "passed", "keywords": ["test_get_persona_defaults_to_maxnet", "test_personas.py", "unit", "tests", "public-script-server", ""], "setup": {"duration": 7.23399999742469e-05, "outcome": "passed"}, "call": {"duration": 7.751700002245343e-05, "outcome": "passed"}, "teardown": {"duration": 8.320199992795096e-05, "outcome": "passed"}}]}