{"created": 1781069168.6550145, "duration": 0.06995606422424316, "exitcode": 0, "root": "/home/runner/work/public-script-server/public-script-server", "environment": {}, "summary": {"passed": 9, "total": 9, "collected": 9}, "collectors": [{"nodeid": "", "outcome": "passed", "result": [{"nodeid": ".", "type": "Dir"}]}, {"nodeid": "reports/history", "outcome": "passed", "result": []}, {"nodeid": "reports", "outcome": "passed", "result": [{"nodeid": "reports/history", "type": "Dir"}]}, {"nodeid": "static/answers", "outcome": "passed", "result": []}, {"nodeid": "static/audio", "outcome": "passed", "result": []}, {"nodeid": "static", "outcome": "passed", "result": [{"nodeid": "static/answers", "type": "Dir"}, {"nodeid": "static/audio", "type": "Dir"}]}, {"nodeid": "templates", "outcome": "passed", "result": []}, {"nodeid": "tests/api/test_basic_routes.py", "outcome": "passed", "result": [{"nodeid": "tests/api/test_basic_routes.py::test_homepage_loads", "type": "Function", "lineno": 0}, {"nodeid": "tests/api/test_basic_routes.py::test_personas_endpoint", "type": "Function", "lineno": 4}, {"nodeid": "tests/api/test_basic_routes.py::test_sass_returns_line", "type": "Function", "lineno": 11}]}, {"nodeid": "tests/api/test_chat.py", "outcome": "passed", "result": [{"nodeid": "tests/api/test_chat.py::test_chat_returns_reply", "type": "Function", "lineno": 2}]}, {"nodeid": "tests/api/test_walkie.py", "outcome": "passed", "result": [{"nodeid": "tests/api/test_walkie.py::test_walkie_locked_persona", "type": "Function", "lineno": 0}]}, {"nodeid": "tests/api", "outcome": "passed", "result": [{"nodeid": "tests/api/test_basic_routes.py", "type": "Module"}, {"nodeid": "tests/api/test_chat.py", "type": "Module"}, {"nodeid": "tests/api/test_walkie.py", "type": "Module"}]}, {"nodeid": "tests/unit/test_personas.py", "outcome": "passed", "result": [{"nodeid": "tests/unit/test_personas.py::test_default_persona_unlocked", "type": "Function", "lineno": 2}, {"nodeid": "tests/unit/test_personas.py::test_elissatron_locked_without_key", "type": "Function", "lineno": 5}, {"nodeid": "tests/unit/test_personas.py::test_elissatron_unlocks_with_correct_key", "type": "Function", "lineno": 9}, {"nodeid": "tests/unit/test_personas.py::test_get_persona_defaults_to_maxnet", "type": "Function", "lineno": 13}]}, {"nodeid": "tests/unit", "outcome": "passed", "result": [{"nodeid": "tests/unit/test_personas.py", "type": "Module"}]}, {"nodeid": "tests", "outcome": "passed", "result": [{"nodeid": "tests/api", "type": "Dir"}, {"nodeid": "tests/unit", "type": "Dir"}]}, {"nodeid": ".", "outcome": "passed", "result": [{"nodeid": "reports", "type": "Dir"}, {"nodeid": "static", "type": "Dir"}, {"nodeid": "templates", "type": "Dir"}, {"nodeid": "tests", "type": "Package"}]}], "tests": [{"nodeid": "tests/api/test_basic_routes.py::test_homepage_loads", "lineno": 0, "outcome": "passed", "keywords": ["test_homepage_loads", "test_basic_routes.py", "api", "tests", "public-script-server", ""], "setup": {"duration": 0.0016896829999950569, "outcome": "passed"}, "call": {"duration": 0.014821173000001409, "outcome": "passed"}, "teardown": {"duration": 0.00016637099997751648, "outcome": "passed"}}, {"nodeid": "tests/api/test_basic_routes.py::test_personas_endpoint", "lineno": 4, "outcome": "passed", "keywords": ["test_personas_endpoint", "test_basic_routes.py", "api", "tests", "public-script-server", ""], "setup": {"duration": 0.00026601600001185943, "outcome": "passed"}, "call": {"duration": 0.0006492419999801768, "outcome": "passed"}, "teardown": {"duration": 0.00014220500000305947, "outcome": "passed"}}, {"nodeid": "tests/api/test_basic_routes.py::test_sass_returns_line", "lineno": 11, "outcome": "passed", "keywords": ["test_sass_returns_line", "test_basic_routes.py", "api", "tests", "public-script-server", ""], "setup": {"duration": 0.0002534529999991264, "outcome": "passed"}, "call": {"duration": 0.0005275639999808845, "outcome": "passed"}, "teardown": {"duration": 0.00016248299999688243, "outcome": "passed"}}, {"nodeid": "tests/api/test_chat.py::test_chat_returns_reply", "lineno": 2, "outcome": "passed", "keywords": ["test_chat_returns_reply", "__wrapped__", "patchings", "test_chat.py", "api", "tests", "public-script-server", ""], "setup": {"duration": 0.0002800430000036158, "outcome": "passed"}, "call": {"duration": 0.0012924920000045859, "outcome": "passed"}, "teardown": {"duration": 0.00013698600000111583, "outcome": "passed"}}, {"nodeid": "tests/api/test_walkie.py::test_walkie_locked_persona", "lineno": 0, "outcome": "passed", "keywords": ["test_walkie_locked_persona", "test_walkie.py", "api", "tests", "public-script-server", ""], "setup": {"duration": 0.00026517500000977634, "outcome": "passed"}, "call": {"duration": 0.001229614000010315, "outcome": "passed"}, "teardown": {"duration": 0.0001346210000008341, "outcome": "passed"}}, {"nodeid": "tests/unit/test_personas.py::test_default_persona_unlocked", "lineno": 2, "outcome": "passed", "keywords": ["test_default_persona_unlocked", "test_personas.py", "unit", "tests", "public-script-server", ""], "setup": {"duration": 0.00017831299999215844, "outcome": "passed"}, "call": {"duration": 0.00012014499998258543, "outcome": "passed"}, "teardown": {"duration": 0.00010228099998244033, "outcome": "passed"}}, {"nodeid": "tests/unit/test_personas.py::test_elissatron_locked_without_key", "lineno": 5, "outcome": "passed", "keywords": ["test_elissatron_locked_without_key", "test_personas.py", "unit", "tests", "public-script-server", ""], "setup": {"duration": 0.0001451400000007652, "outcome": "passed"}, "call": {"duration": 0.00012584500001366905, "outcome": "passed"}, "teardown": {"duration": 0.00011796000001140783, "outcome": "passed"}}, {"nodeid": "tests/unit/test_personas.py::test_elissatron_unlocks_with_correct_key", "lineno": 9, "outcome": "passed", "keywords": ["test_elissatron_unlocks_with_correct_key", "test_personas.py", "unit", "tests", "public-script-server", ""], "setup": {"duration": 0.0001413439999851107, "outcome": "passed"}, "call": {"duration": 0.00014413899998544366, "outcome": "passed"}, "teardown": {"duration": 0.00012060500000643515, "outcome": "passed"}}, {"nodeid": "tests/unit/test_personas.py::test_get_persona_defaults_to_maxnet", "lineno": 13, "outcome": "passed", "keywords": ["test_get_persona_defaults_to_maxnet", "test_personas.py", "unit", "tests", "public-script-server", ""], "setup": {"duration": 0.00010080799998490875, "outcome": "passed"}, "call": {"duration": 0.0001169679999861728, "outcome": "passed"}, "teardown": {"duration": 0.00011910199998510507, "outcome": "passed"}}]}