{"created": 1768940471.221484, "duration": 0.08124160766601562, "exitcode": 0, "root": "/home/runner/work/public-script-server/public-script-server", "environment": {}, "summary": {"passed": 9, "total": 9, "collected": 9}, "collectors": [{"nodeid": "", "outcome": "passed", "result": [{"nodeid": ".", "type": "Dir"}]}, {"nodeid": "reports/history", "outcome": "passed", "result": []}, {"nodeid": "reports", "outcome": "passed", "result": [{"nodeid": "reports/history", "type": "Dir"}]}, {"nodeid": "static/answers", "outcome": "passed", "result": []}, {"nodeid": "static/audio", "outcome": "passed", "result": []}, {"nodeid": "static", "outcome": "passed", "result": [{"nodeid": "static/answers", "type": "Dir"}, {"nodeid": "static/audio", "type": "Dir"}]}, {"nodeid": "templates", "outcome": "passed", "result": []}, {"nodeid": "tests/api/test_basic_routes.py", "outcome": "passed", "result": [{"nodeid": "tests/api/test_basic_routes.py::test_homepage_loads", "type": "Function", "lineno": 0}, {"nodeid": "tests/api/test_basic_routes.py::test_personas_endpoint", "type": "Function", "lineno": 4}, {"nodeid": "tests/api/test_basic_routes.py::test_sass_returns_line", "type": "Function", "lineno": 11}]}, {"nodeid": "tests/api/test_chat.py", "outcome": "passed", "result": [{"nodeid": "tests/api/test_chat.py::test_chat_returns_reply", "type": "Function", "lineno": 2}]}, {"nodeid": "tests/api/test_walkie.py", "outcome": "passed", "result": [{"nodeid": "tests/api/test_walkie.py::test_walkie_locked_persona", "type": "Function", "lineno": 0}]}, {"nodeid": "tests/api", "outcome": "passed", "result": [{"nodeid": "tests/api/test_basic_routes.py", "type": "Module"}, {"nodeid": "tests/api/test_chat.py", "type": "Module"}, {"nodeid": "tests/api/test_walkie.py", "type": "Module"}]}, {"nodeid": "tests/unit/test_personas.py", "outcome": "passed", "result": [{"nodeid": "tests/unit/test_personas.py::test_default_persona_unlocked", "type": "Function", "lineno": 2}, {"nodeid": "tests/unit/test_personas.py::test_elissatron_locked_without_key", "type": "Function", "lineno": 5}, {"nodeid": "tests/unit/test_personas.py::test_elissatron_unlocks_with_correct_key", "type": "Function", "lineno": 9}, {"nodeid": "tests/unit/test_personas.py::test_get_persona_defaults_to_maxnet", "type": "Function", "lineno": 13}]}, {"nodeid": "tests/unit", "outcome": "passed", "result": [{"nodeid": "tests/unit/test_personas.py", "type": "Module"}]}, {"nodeid": "tests", "outcome": "passed", "result": [{"nodeid": "tests/api", "type": "Dir"}, {"nodeid": "tests/unit", "type": "Dir"}]}, {"nodeid": ".", "outcome": "passed", "result": [{"nodeid": "reports", "type": "Dir"}, {"nodeid": "static", "type": "Dir"}, {"nodeid": "templates", "type": "Dir"}, {"nodeid": "tests", "type": "Package"}]}], "tests": [{"nodeid": "tests/api/test_basic_routes.py::test_homepage_loads", "lineno": 0, "outcome": "passed", "keywords": ["test_homepage_loads", "test_basic_routes.py", "api", "tests", "public-script-server", ""], "setup": {"duration": 0.0015836859999964759, "outcome": "passed"}, "call": {"duration": 0.01496005500000308, "outcome": "passed"}, "teardown": {"duration": 0.00016645000000181653, "outcome": "passed"}}, {"nodeid": "tests/api/test_basic_routes.py::test_personas_endpoint", "lineno": 4, "outcome": "passed", "keywords": ["test_personas_endpoint", "test_basic_routes.py", "api", "tests", "public-script-server", ""], "setup": {"duration": 0.00024311199999971222, "outcome": "passed"}, "call": {"duration": 0.0005746689999952537, "outcome": "passed"}, "teardown": {"duration": 0.000129340999997396, "outcome": "passed"}}, {"nodeid": "tests/api/test_basic_routes.py::test_sass_returns_line", "lineno": 11, "outcome": "passed", "keywords": ["test_sass_returns_line", "test_basic_routes.py", "api", "tests", "public-script-server", ""], "setup": {"duration": 0.0002129760000002534, "outcome": "passed"}, "call": {"duration": 0.00047297900000131676, "outcome": "passed"}, "teardown": {"duration": 0.00013516100000288134, "outcome": "passed"}}, {"nodeid": "tests/api/test_chat.py::test_chat_returns_reply", "lineno": 2, "outcome": "passed", "keywords": ["test_chat_returns_reply", "__wrapped__", "patchings", "test_chat.py", "api", "tests", "public-script-server", ""], "setup": {"duration": 0.0002562170000004471, "outcome": "passed"}, "call": {"duration": 0.0012063739999987888, "outcome": "passed"}, "teardown": {"duration": 0.00013026300000262836, "outcome": "passed"}}, {"nodeid": "tests/api/test_walkie.py::test_walkie_locked_persona", "lineno": 0, "outcome": "passed", "keywords": ["test_walkie_locked_persona", "test_walkie.py", "api", "tests", "public-script-server", ""], "setup": {"duration": 0.00027244600000386754, "outcome": "passed"}, "call": {"duration": 0.0012078469999963204, "outcome": "passed"}, "teardown": {"duration": 0.00012929100000036442, "outcome": "passed"}}, {"nodeid": "tests/unit/test_personas.py::test_default_persona_unlocked", "lineno": 2, "outcome": "passed", "keywords": ["test_default_persona_unlocked", "test_personas.py", "unit", "tests", "public-script-server", ""], "setup": {"duration": 0.00016448600000273927, "outcome": "passed"}, "call": {"duration": 0.00011348099999963779, "outcome": "passed"}, "teardown": {"duration": 9.616900000253281e-05, "outcome": "passed"}}, {"nodeid": "tests/unit/test_personas.py::test_elissatron_locked_without_key", "lineno": 5, "outcome": "passed", "keywords": ["test_elissatron_locked_without_key", "test_personas.py", "unit", "tests", "public-script-server", ""], "setup": {"duration": 0.00013768600000219067, "outcome": "passed"}, "call": {"duration": 0.00012474100000048338, "outcome": "passed"}, "teardown": {"duration": 0.00011240900000331067, "outcome": "passed"}}, {"nodeid": "tests/unit/test_personas.py::test_elissatron_unlocks_with_correct_key", "lineno": 9, "outcome": "passed", "keywords": ["test_elissatron_unlocks_with_correct_key", "test_personas.py", "unit", "tests", "public-script-server", ""], "setup": {"duration": 0.0001381660000063789, "outcome": "passed"}, "call": {"duration": 0.00013095399999940582, "outcome": "passed"}, "teardown": {"duration": 0.00011730800000009367, "outcome": "passed"}}, {"nodeid": "tests/unit/test_personas.py::test_get_persona_defaults_to_maxnet", "lineno": 13, "outcome": "passed", "keywords": ["test_get_persona_defaults_to_maxnet", "test_personas.py", "unit", "tests", "public-script-server", ""], "setup": {"duration": 9.870299999903409e-05, "outcome": "passed"}, "call": {"duration": 0.0001151539999995066, "outcome": "passed"}, "teardown": {"duration": 0.0001133810000055746, "outcome": "passed"}}]}