{"created": 1772798597.1389773, "duration": 0.09946131706237793, "exitcode": 0, "root": "/home/runner/work/public-script-server/public-script-server", "environment": {}, "summary": {"passed": 9, "total": 9, "collected": 9}, "collectors": [{"nodeid": "", "outcome": "passed", "result": [{"nodeid": ".", "type": "Dir"}]}, {"nodeid": "reports/history", "outcome": "passed", "result": []}, {"nodeid": "reports", "outcome": "passed", "result": [{"nodeid": "reports/history", "type": "Dir"}]}, {"nodeid": "static/answers", "outcome": "passed", "result": []}, {"nodeid": "static/audio", "outcome": "passed", "result": []}, {"nodeid": "static", "outcome": "passed", "result": [{"nodeid": "static/answers", "type": "Dir"}, {"nodeid": "static/audio", "type": "Dir"}]}, {"nodeid": "templates", "outcome": "passed", "result": []}, {"nodeid": "tests/api/test_basic_routes.py", "outcome": "passed", "result": [{"nodeid": "tests/api/test_basic_routes.py::test_homepage_loads", "type": "Function", "lineno": 0}, {"nodeid": "tests/api/test_basic_routes.py::test_personas_endpoint", "type": "Function", "lineno": 4}, {"nodeid": "tests/api/test_basic_routes.py::test_sass_returns_line", "type": "Function", "lineno": 11}]}, {"nodeid": "tests/api/test_chat.py", "outcome": "passed", "result": [{"nodeid": "tests/api/test_chat.py::test_chat_returns_reply", "type": "Function", "lineno": 2}]}, {"nodeid": "tests/api/test_walkie.py", "outcome": "passed", "result": [{"nodeid": "tests/api/test_walkie.py::test_walkie_locked_persona", "type": "Function", "lineno": 0}]}, {"nodeid": "tests/api", "outcome": "passed", "result": [{"nodeid": "tests/api/test_basic_routes.py", "type": "Module"}, {"nodeid": "tests/api/test_chat.py", "type": "Module"}, {"nodeid": "tests/api/test_walkie.py", "type": "Module"}]}, {"nodeid": "tests/unit/test_personas.py", "outcome": "passed", "result": [{"nodeid": "tests/unit/test_personas.py::test_default_persona_unlocked", "type": "Function", "lineno": 2}, {"nodeid": "tests/unit/test_personas.py::test_elissatron_locked_without_key", "type": "Function", "lineno": 5}, {"nodeid": "tests/unit/test_personas.py::test_elissatron_unlocks_with_correct_key", "type": "Function", "lineno": 9}, {"nodeid": "tests/unit/test_personas.py::test_get_persona_defaults_to_maxnet", "type": "Function", "lineno": 13}]}, {"nodeid": "tests/unit", "outcome": "passed", "result": [{"nodeid": "tests/unit/test_personas.py", "type": "Module"}]}, {"nodeid": "tests", "outcome": "passed", "result": [{"nodeid": "tests/api", "type": "Dir"}, {"nodeid": "tests/unit", "type": "Dir"}]}, {"nodeid": ".", "outcome": "passed", "result": [{"nodeid": "reports", "type": "Dir"}, {"nodeid": "static", "type": "Dir"}, {"nodeid": "templates", "type": "Dir"}, {"nodeid": "tests", "type": "Package"}]}], "tests": [{"nodeid": "tests/api/test_basic_routes.py::test_homepage_loads", "lineno": 0, "outcome": "passed", "keywords": ["test_homepage_loads", "test_basic_routes.py", "api", "tests", "public-script-server", ""], "setup": {"duration": 0.0017322820000060801, "outcome": "passed"}, "call": {"duration": 0.014971832000000518, "outcome": "passed"}, "teardown": {"duration": 0.00019031700000482488, "outcome": "passed"}}, {"nodeid": "tests/api/test_basic_routes.py::test_personas_endpoint", "lineno": 4, "outcome": "passed", "keywords": ["test_personas_endpoint", "test_basic_routes.py", "api", "tests", "public-script-server", ""], "setup": {"duration": 0.00031311600000094586, "outcome": "passed"}, "call": {"duration": 0.0006619990000018561, "outcome": "passed"}, "teardown": {"duration": 0.00014574299999736695, "outcome": "passed"}}, {"nodeid": "tests/api/test_basic_routes.py::test_sass_returns_line", "lineno": 11, "outcome": "passed", "keywords": ["test_sass_returns_line", "test_basic_routes.py", "api", "tests", "public-script-server", ""], "setup": {"duration": 0.00025932599999833883, "outcome": "passed"}, "call": {"duration": 0.000509213000000841, "outcome": "passed"}, "teardown": {"duration": 0.00014218600000504011, "outcome": "passed"}}, {"nodeid": "tests/api/test_chat.py::test_chat_returns_reply", "lineno": 2, "outcome": "passed", "keywords": ["test_chat_returns_reply", "__wrapped__", "patchings", "test_chat.py", "api", "tests", "public-script-server", ""], "setup": {"duration": 0.0003138480000046684, "outcome": "passed"}, "call": {"duration": 0.0014041989999995508, "outcome": "passed"}, "teardown": {"duration": 0.00014039299999524246, "outcome": "passed"}}, {"nodeid": "tests/api/test_walkie.py::test_walkie_locked_persona", "lineno": 0, "outcome": "passed", "keywords": ["test_walkie_locked_persona", "test_walkie.py", "api", "tests", "public-script-server", ""], "setup": {"duration": 0.00033045800000053305, "outcome": "passed"}, "call": {"duration": 0.001266631000000018, "outcome": "passed"}, "teardown": {"duration": 0.00014043299999855208, "outcome": "passed"}}, {"nodeid": "tests/unit/test_personas.py::test_default_persona_unlocked", "lineno": 2, "outcome": "passed", "keywords": ["test_default_persona_unlocked", "test_personas.py", "unit", "tests", "public-script-server", ""], "setup": {"duration": 0.00016785400000429718, "outcome": "passed"}, "call": {"duration": 0.00012737799999484878, "outcome": "passed"}, "teardown": {"duration": 0.00011107799999621193, "outcome": "passed"}}, {"nodeid": "tests/unit/test_personas.py::test_elissatron_locked_without_key", "lineno": 5, "outcome": "passed", "keywords": ["test_elissatron_locked_without_key", "test_personas.py", "unit", "tests", "public-script-server", ""], "setup": {"duration": 0.00015344700000241573, "outcome": "passed"}, "call": {"duration": 0.00012461300000410347, "outcome": "passed"}, "teardown": {"duration": 0.00012393200000104798, "outcome": "passed"}}, {"nodeid": "tests/unit/test_personas.py::test_elissatron_unlocks_with_correct_key", "lineno": 9, "outcome": "passed", "keywords": ["test_elissatron_unlocks_with_correct_key", "test_personas.py", "unit", "tests", "public-script-server", ""], "setup": {"duration": 0.0001664919999981862, "outcome": "passed"}, "call": {"duration": 0.0001397519999954966, "outcome": "passed"}, "teardown": {"duration": 0.00012573600000109764, "outcome": "passed"}}, {"nodeid": "tests/unit/test_personas.py::test_get_persona_defaults_to_maxnet", "lineno": 13, "outcome": "passed", "keywords": ["test_get_persona_defaults_to_maxnet", "test_personas.py", "unit", "tests", "public-script-server", ""], "setup": {"duration": 0.0001088629999941304, "outcome": "passed"}, "call": {"duration": 0.00015379799999948318, "outcome": "passed"}, "teardown": {"duration": 0.0001038039999983198, "outcome": "passed"}}]}