{"created": 1770249864.7798371, "duration": 0.15117955207824707, "exitcode": 0, "root": "/home/runner/work/public-script-server/public-script-server", "environment": {}, "summary": {"passed": 9, "total": 9, "collected": 9}, "collectors": [{"nodeid": "", "outcome": "passed", "result": [{"nodeid": ".", "type": "Dir"}]}, {"nodeid": "reports/history", "outcome": "passed", "result": []}, {"nodeid": "reports", "outcome": "passed", "result": [{"nodeid": "reports/history", "type": "Dir"}]}, {"nodeid": "static/answers", "outcome": "passed", "result": []}, {"nodeid": "static/audio", "outcome": "passed", "result": []}, {"nodeid": "static", "outcome": "passed", "result": [{"nodeid": "static/answers", "type": "Dir"}, {"nodeid": "static/audio", "type": "Dir"}]}, {"nodeid": "templates", "outcome": "passed", "result": []}, {"nodeid": "tests/api/test_basic_routes.py", "outcome": "passed", "result": [{"nodeid": "tests/api/test_basic_routes.py::test_homepage_loads", "type": "Function", "lineno": 0}, {"nodeid": "tests/api/test_basic_routes.py::test_personas_endpoint", "type": "Function", "lineno": 4}, {"nodeid": "tests/api/test_basic_routes.py::test_sass_returns_line", "type": "Function", "lineno": 11}]}, {"nodeid": "tests/api/test_chat.py", "outcome": "passed", "result": [{"nodeid": "tests/api/test_chat.py::test_chat_returns_reply", "type": "Function", "lineno": 2}]}, {"nodeid": "tests/api/test_walkie.py", "outcome": "passed", "result": [{"nodeid": "tests/api/test_walkie.py::test_walkie_locked_persona", "type": "Function", "lineno": 0}]}, {"nodeid": "tests/api", "outcome": "passed", "result": [{"nodeid": "tests/api/test_basic_routes.py", "type": "Module"}, {"nodeid": "tests/api/test_chat.py", "type": "Module"}, {"nodeid": "tests/api/test_walkie.py", "type": "Module"}]}, {"nodeid": "tests/unit/test_personas.py", "outcome": "passed", "result": [{"nodeid": "tests/unit/test_personas.py::test_default_persona_unlocked", "type": "Function", "lineno": 2}, {"nodeid": "tests/unit/test_personas.py::test_elissatron_locked_without_key", "type": "Function", "lineno": 5}, {"nodeid": "tests/unit/test_personas.py::test_elissatron_unlocks_with_correct_key", "type": "Function", "lineno": 9}, {"nodeid": "tests/unit/test_personas.py::test_get_persona_defaults_to_maxnet", "type": "Function", "lineno": 13}]}, {"nodeid": "tests/unit", "outcome": "passed", "result": [{"nodeid": "tests/unit/test_personas.py", "type": "Module"}]}, {"nodeid": "tests", "outcome": "passed", "result": [{"nodeid": "tests/api", "type": "Dir"}, {"nodeid": "tests/unit", "type": "Dir"}]}, {"nodeid": ".", "outcome": "passed", "result": [{"nodeid": "reports", "type": "Dir"}, {"nodeid": "static", "type": "Dir"}, {"nodeid": "templates", "type": "Dir"}, {"nodeid": "tests", "type": "Package"}]}], "tests": [{"nodeid": "tests/api/test_basic_routes.py::test_homepage_loads", "lineno": 0, "outcome": "passed", "keywords": ["test_homepage_loads", "test_basic_routes.py", "api", "tests", "public-script-server", ""], "setup": {"duration": 0.0017920319999973344, "outcome": "passed"}, "call": {"duration": 0.014391914999997368, "outcome": "passed"}, "teardown": {"duration": 0.00016565699999659955, "outcome": "passed"}}, {"nodeid": "tests/api/test_basic_routes.py::test_personas_endpoint", "lineno": 4, "outcome": "passed", "keywords": ["test_personas_endpoint", "test_basic_routes.py", "api", "tests", "public-script-server", ""], "setup": {"duration": 0.00025614500000159524, "outcome": "passed"}, "call": {"duration": 0.0005346510000023841, "outcome": "passed"}, "teardown": {"duration": 0.00013730399999900555, "outcome": "passed"}}, {"nodeid": "tests/api/test_basic_routes.py::test_sass_returns_line", "lineno": 11, "outcome": "passed", "keywords": ["test_sass_returns_line", "test_basic_routes.py", "api", "tests", "public-script-server", ""], "setup": {"duration": 0.00021484799999882398, "outcome": "passed"}, "call": {"duration": 0.00047751599999656946, "outcome": "passed"}, "teardown": {"duration": 0.00014168200000597153, "outcome": "passed"}}, {"nodeid": "tests/api/test_chat.py::test_chat_returns_reply", "lineno": 2, "outcome": "passed", "keywords": ["test_chat_returns_reply", "__wrapped__", "patchings", "test_chat.py", "api", "tests", "public-script-server", ""], "setup": {"duration": 0.0003022909999970125, "outcome": "passed"}, "call": {"duration": 0.001219620999997062, "outcome": "passed"}, "teardown": {"duration": 0.00013687399999895433, "outcome": "passed"}}, {"nodeid": "tests/api/test_walkie.py::test_walkie_locked_persona", "lineno": 0, "outcome": "passed", "keywords": ["test_walkie_locked_persona", "test_walkie.py", "api", "tests", "public-script-server", ""], "setup": {"duration": 0.00031237900000036234, "outcome": "passed"}, "call": {"duration": 0.0012210639999992168, "outcome": "passed"}, "teardown": {"duration": 0.0001452399999948284, "outcome": "passed"}}, {"nodeid": "tests/unit/test_personas.py::test_default_persona_unlocked", "lineno": 2, "outcome": "passed", "keywords": ["test_default_persona_unlocked", "test_personas.py", "unit", "tests", "public-script-server", ""], "setup": {"duration": 0.00016911299999833318, "outcome": "passed"}, "call": {"duration": 0.00011520300000000816, "outcome": "passed"}, "teardown": {"duration": 9.607800000566158e-05, "outcome": "passed"}}, {"nodeid": "tests/unit/test_personas.py::test_elissatron_locked_without_key", "lineno": 5, "outcome": "passed", "keywords": ["test_elissatron_locked_without_key", "test_personas.py", "unit", "tests", "public-script-server", ""], "setup": {"duration": 0.00014447699999919905, "outcome": "passed"}, "call": {"duration": 0.00011429199999923867, "outcome": "passed"}, "teardown": {"duration": 0.000112317999999334, "outcome": "passed"}}, {"nodeid": "tests/unit/test_personas.py::test_elissatron_unlocks_with_correct_key", "lineno": 9, "outcome": "passed", "keywords": ["test_elissatron_unlocks_with_correct_key", "test_personas.py", "unit", "tests", "public-script-server", ""], "setup": {"duration": 0.00015063899999745445, "outcome": "passed"}, "call": {"duration": 0.00011941199999654373, "outcome": "passed"}, "teardown": {"duration": 0.000115223999998193, "outcome": "passed"}}, {"nodeid": "tests/unit/test_personas.py::test_get_persona_defaults_to_maxnet", "lineno": 13, "outcome": "passed", "keywords": ["test_get_persona_defaults_to_maxnet", "test_personas.py", "unit", "tests", "public-script-server", ""], "setup": {"duration": 9.820199999666102e-05, "outcome": "passed"}, "call": {"duration": 0.00011724699999859922, "outcome": "passed"}, "teardown": {"duration": 9.832199999948443e-05, "outcome": "passed"}}]}